gnnad/__init__.py
gnnad/generate.py
gnnad/graphanomaly.py
gnnad/plot.py
gnnad-0.1.1.dist-info/LICENSE
gnnad-0.1.1.dist-info/METADATA
gnnad-0.1.1.dist-info/WHEEL
gnnad-0.1.1.dist-info/RECORD
