Metadata-Version: 2.1
Name: gnnad
Version: 0.1.1
Summary: Graph Neural Network-Based Anomaly Detection (GNNAD)
Home-page: https://github.com/KatieBuc/gnnad
License: MIT
Author: Katie Buchhorn
Maintainer: Katie Buchhorn
Requires-Python: >=3.8,<3.12
Classifier: License :: OSI Approved :: MIT License
Classifier: Programming Language :: Python :: 3
Classifier: Programming Language :: Python :: 3.8
Classifier: Programming Language :: Python :: 3.9
Classifier: Programming Language :: Python :: 3.10
Classifier: Programming Language :: Python :: 3.11
Requires-Dist: gstools (>=1.4.1,<2.0.0)
Requires-Dist: matplotlib (>=3.7.1,<4.0.0)
Requires-Dist: numpy (>=1.24.2,<2.0.0)
Requires-Dist: pandas (>=1.5.3,<2.0.0)
Requires-Dist: scikit-learn (>=1.2.2,<2.0.0)
Requires-Dist: scipy (>=1.10.1,<2.0.0)
Requires-Dist: torch (>=2.0.0,<3.0.0)
Requires-Dist: torch-geometric (>=2.3.0,<3.0.0)
Requires-Dist: torchsummary (>=1.5.1,<2.0.0)
Project-URL: Repository, https://github.com/KatieBuc/gnnad
